kitefly/__init__.py
kitefly/util.py
kitefly/filter/__init__.py
kitefly/filter/filter.py
kitefly/filter/git_filter.py
kitefly/filter/noop_filter.py
kitefly/model/__init__.py
kitefly/model/command.py
kitefly/model/group.py
kitefly/model/input.py
kitefly/model/pipeline.py
kitefly/model/plugin.py
kitefly/model/retry.py
kitefly/model/step.py
kitefly/model/target.py
kitefly/model/trigger.py
kitefly/model/wait.py
kitefly-0.1.0.dist-info/LICENSE.md
kitefly-0.1.0.dist-info/METADATA
kitefly-0.1.0.dist-info/WHEEL
kitefly-0.1.0.dist-info/top_level.txt
kitefly-0.1.0.dist-info/RECORD
