Metadata-Version: 2.1
Name: kitefly
Version: 0.1.0
Summary: Generate Buildkite YAML with composable type-checked models
Home-page: https://github.com/pytown/kitefly
Author: Chris Carpita
Author-email: ccarpita@gmail.com
License: UNKNOWN
Project-URL: Bug Tracker, https://github.com/pytown/kitefly/issues
Platform: UNKNOWN
Classifier: Programming Language :: Python :: 3
Classifier: License :: OSI Approved :: MIT License
Classifier: Operating System :: OS Independent
Requires-Python: >=3.7
License-File: LICENSE.md
Requires-Dist: pyyaml
